{
  "db_name": "PostgreSQL",
  "query": "\n            SELECT \n                id,\n                name,\n                type,\n                on_budget,\n                closed,\n                note,\n                balance,\n                cleared_balance,\n                uncleared_balance,\n                transfer_payee_id,\n                direct_import_linked,\n                direct_import_in_error,\n                deleted,\n                last_reconciled_at,\n                debt_original_balance,\n                debt_interest_rates,\n                debt_minimum_payments,\n                debt_escrow_amounts\n            FROM accounts\n            ",
  "describe": {
    "columns": [
      {
        "ordinal": 0,
        "name": "id",
        "type_info": "Uuid"
      },
      {
        "ordinal": 1,
        "name": "name",
        "type_info": "Text"
      },
      {
        "ordinal": 2,
        "name": "type",
        "type_info": "Varchar"
      },
      {
        "ordinal": 3,
        "name": "on_budget",
        "type_info": "Bool"
      },
      {
        "ordinal": 4,
        "name": "closed",
        "type_info": "Bool"
      },
      {
        "ordinal": 5,
        "name": "note",
        "type_info": "Text"
      },
      {
        "ordinal": 6,
        "name": "balance",
        "type_info": "Int8"
      },
      {
        "ordinal": 7,
        "name": "cleared_balance",
        "type_info": "Int8"
      },
      {
        "ordinal": 8,
        "name": "uncleared_balance",
        "type_info": "Int8"
      },
      {
        "ordinal": 9,
        "name": "transfer_payee_id",
        "type_info": "Uuid"
      },
      {
        "ordinal": 10,
        "name": "direct_import_linked",
        "type_info": "Bool"
      },
      {
        "ordinal": 11,
        "name": "direct_import_in_error",
        "type_info": "Bool"
      },
      {
        "ordinal": 12,
        "name": "deleted",
        "type_info": "Bool"
      },
      {
        "ordinal": 13,
        "name": "last_reconciled_at",
        "type_info": "Timestamptz"
      },
      {
        "ordinal": 14,
        "name": "debt_original_balance",
        "type_info": "Int8"
      },
      {
        "ordinal": 15,
        "name": "debt_interest_rates",
        "type_info": "Jsonb"
      },
      {
        "ordinal": 16,
        "name": "debt_minimum_payments",
        "type_info": "Jsonb"
      },
      {
        "ordinal": 17,
        "name": "debt_escrow_amounts",
        "type_info": "Jsonb"
      }
    ],
    "parameters": {
      "Left": []
    },
    "nullable": [
      false,
      false,
      false,
      false,
      false,
      true,
      false,
      false,
      false,
      false,
      true,
      true,
      false,
      true,
      true,
      false,
      false,
      false
    ]
  },
  "hash": "4b677dbe44951b6dfd370011b27bb3dde65e04886d261853f1a426928b54e9d3"
}
